libname/__init__.py
libname/hello.py
simple_hello_package-0.0.4.dist-info/METADATA
simple_hello_package-0.0.4.dist-info/WHEEL
simple_hello_package-0.0.4.dist-info/top_level.txt
simple_hello_package-0.0.4.dist-info/RECORD
