Metadata-Version: 2.1
Name: simple-hello-package
Version: 0.0.4
Summary: Basic hello package
Home-page: UNKNOWN
Author: Hirokazu Hirono
Author-email: <hirono.hirokazu@gmail.com>
License: UNKNOWN
Keywords: python,video,stream,video stream,camera stream,sockets
Platform: UNKNOWN
Classifier: Development Status :: 1 - Planning
Classifier: Intended Audience :: Developers
Classifier: Programming Language :: Python :: 3
Classifier: Operating System :: Unix
Classifier: Operating System :: MacOS :: MacOS X
Classifier: Operating System :: Microsoft :: Windows
